creatio_connector/__init__.py
creatio_connector/creatio.py
creatio_connector_sumarokov-0.0.2.dist-info/LICENSE
creatio_connector_sumarokov-0.0.2.dist-info/METADATA
creatio_connector_sumarokov-0.0.2.dist-info/WHEEL
creatio_connector_sumarokov-0.0.2.dist-info/top_level.txt
creatio_connector_sumarokov-0.0.2.dist-info/RECORD
