Metadata-Version: 2.1
Name: creatio-connector-sumarokov
Version: 0.0.2
Summary: Connector to your Creatio project (https://www.creatio.com)
Home-page: https://github.com/sumarokov-vp/py_creatio_connector
Author: Vladimir Sumarokov
Author-email: sumarokov.vp@gmail.com
License: UNKNOWN
Platform: UNKNOWN
Classifier: Programming Language :: Python :: 3
Classifier: License :: OSI Approved :: MIT License
Classifier: Operating System :: OS Independent
Requires-Python: >=3.6
